ngsqc/__init__.py
ngsqc/config.py
ngsqc/config.py.py
ngsqc/arranger/__init__.py
ngsqc/arranger/arranger.py
ngsqc/arranger/config.py
ngsqc/bamqc/BamQC.py
ngsqc/bamqc/__init__.py
ngsqc/fastqc/FastQC.py
ngsqc/fastqc/__init__.py
ngsqc/fastqc/config.py
ngsqc/fastqc/fast_qc.py
ngsqc/fastqc/fastp.py
ngsqc/fastqc/fastp2table.py
ngsqc/reporter/__init__.py
ngsqc/reporter/config.py
ngsqc/reporter/mkdocsTemplate.tgz
ngsqc/reporter/render.py
ngsqc/reporter/reporter.py
ngsqc/reporter/template.md
ngsqc/vcfqc/VcfQC.py
ngsqc/vcfqc/__init__.py
ngsqc-0.1.5.data/scripts/fastQc.py
ngsqc-0.1.5.data/scripts/smartFqs.py
ngsqc-0.1.5.dist-info/DESCRIPTION.rst
ngsqc-0.1.5.dist-info/METADATA
ngsqc-0.1.5.dist-info/RECORD
ngsqc-0.1.5.dist-info/WHEEL
ngsqc-0.1.5.dist-info/metadata.json
ngsqc-0.1.5.dist-info/top_level.txt
