Metadata-Version: 2.0
Name: ngsqc
Version: 0.1.5
Summary: Add a short description here!
Home-page: http://...
Author: KongDeju
Author-email: kongdeju@gene.ac
License: none
Platform: UNKNOWN
Classifier: Development Status :: 4 - Beta
Classifier: Programming Language :: Python
